<annotation>
	<folder>dogestouse</folder>
	<filename>renames_184.jpg</filename>
	<path>C:\Users\Justin\Downloads\dogestouse\renames_184.jpg</path>
	<source>
		<database>Unknown</database>
	</source>
	<size>
		<width>236</width>
		<height>318</height>
		<depth>3</depth>
	</size>
	<segmented>0</segmented>
	<object>
		<name>doge</name>
		<pose>Unspecified</pose>
		<truncated>0</truncated>
		<difficult>0</difficult>
		<bndbox>
			<xmin>152</xmin>
			<ymin>166</ymin>
			<xmax>230</xmax>
			<ymax>250</ymax>
		</bndbox>
	</object>
</annotation>
